gestore/__init__.py
gestore/apps.py
gestore/encoders.py
gestore/gestore_command.py
gestore/processors.py
gestore/typing.py
gestore/utils.py
gestore/management/__init__.py
gestore/management/commands/__init__.py
gestore/management/commands/deleteobjects.py
gestore/management/commands/exportobjects.py
gestore/management/commands/importobjects.py
gestore/migrations/__init__.py
gestore-0.1.0.dev4.dist-info/LICENSE
gestore-0.1.0.dev4.dist-info/METADATA
gestore-0.1.0.dev4.dist-info/WHEEL
gestore-0.1.0.dev4.dist-info/top_level.txt
gestore-0.1.0.dev4.dist-info/RECORD
