Metadata-Version: 2.1
Name: gestore
Version: 0.1.0.dev4
Summary: Django object management
Home-page: https://github.com/appsembler/gestore
Author: Appsembler
Author-email: ops@appsembler.com
License: UNKNOWN
Project-URL: Bug Tracker, https://github.com/appsembler/gestore/issues
Platform: UNKNOWN
Classifier: Development Status :: 1 - Planning
Classifier: Intended Audience :: Developers
Classifier: Operating System :: OS Independent
Classifier: License :: OSI Approved :: MIT License
Classifier: Topic :: Software Development :: Libraries :: Python Modules
Classifier: Programming Language :: Python
Classifier: Programming Language :: Python :: 3.5
Classifier: Programming Language :: Python :: 3.8
Classifier: Programming Language :: Python :: 3.9
Classifier: Framework :: Django
Classifier: Framework :: Django :: 2.2
Classifier: Framework :: Django :: 3.0
Classifier: Framework :: Django :: 3.1
Classifier: Framework :: Django :: 3.2
Requires-Python: >=3.5
License-File: LICENSE
